djangonepal/__init__.py
djangonepal/admin.py
djangonepal/apps.py
djangonepal/context_processors.py
djangonepal/models.py
djangonepal/tests.py
djangonepal/views.py
djangonepal/scripts/__init__.py
djangonepal/scripts/load_data.py
djangonepal-0.0.9.dist-info/LICENSE
djangonepal-0.0.9.dist-info/METADATA
djangonepal-0.0.9.dist-info/WHEEL
djangonepal-0.0.9.dist-info/top_level.txt
djangonepal-0.0.9.dist-info/RECORD
