Metadata-Version: 2.1
Name: djangonepal
Version: 0.0.9
Summary: A Django app that provides choices for adminstrative bodies of Nepal.
Home-page: https://github.com/AtitBimali/django-nepal
Author: Atit Bimali
Author-email: atitbimali@gmail.com
License: MIT
Classifier: Environment :: Web Environment
Classifier: Framework :: Django
Classifier: Intended Audience :: Developers
Classifier: License :: OSI Approved :: MIT License
Classifier: Operating System :: OS Independent
Classifier: Programming Language :: Python
Classifier: Programming Language :: Python :: 3
Classifier: Programming Language :: Python :: 3 :: Only
Classifier: Programming Language :: Python :: 3.8
Classifier: Programming Language :: Python :: 3.9
Classifier: Topic :: Software Development :: Libraries :: Application Frameworks
Classifier: Topic :: Software Development :: Libraries :: Python Modules
Requires-Python: >=3.8
License-File: LICENSE
Requires-Dist: Django >=3.0
Requires-Dist: django-extensions >=3.2.0
